MANIFEST.in
README.md
setup.py
attachments/__init__.py
attachments/forms.py
attachments/models.py
attachments/urls.py
attachments/utils.py
attachments/views.py
attachments/locale/uk/LC_MESSAGES/django.mo
attachments/locale/uk/LC_MESSAGES/django.po
attachments/static/attachments/file-manager.css
attachments/static/attachments/file-manager.js
attachments/static/attachments/spinner.gif
attachments/static/dropzone/dropzone.min.css
attachments/static/dropzone/dropzone.min.js
attachments/templates/attachments/field.html
django_mp_attachments.egg-info/PKG-INFO
django_mp_attachments.egg-info/SOURCES.txt
django_mp_attachments.egg-info/dependency_links.txt
django_mp_attachments.egg-info/top_level.txt