Metadata-Version: 2.1
Name: django-mp-attachments
Version: 0.0.1
Summary: Django attachments app
Home-page: https://github.com/pmaigutyak/mp-attachments
Download-URL: https://github.com/pmaigutyak/mp-attachments/archive/0.0.1.tar.gz
Author: Paul Maigutyak
Author-email: pmaigutyak@gmail.com
License: MIT
